conintf_ptk/__init__.py
conintf_ptk/console.py
conintf_ptk-1.3.0.dist-info/licenses/LICENSE
conintf_ptk-1.3.0.dist-info/METADATA
conintf_ptk-1.3.0.dist-info/WHEEL
conintf_ptk-1.3.0.dist-info/top_level.txt
conintf_ptk-1.3.0.dist-info/RECORD
