Metadata-Version: 2.4
Name: conintf_ptk
Version: 1.3.0
Summary: Lightweight async console interface wrapper around prompt_toolkit
Home-page: https://github.com/TonpalmUnmain/conintf_ptk
Author: Warat Thongsuwan
Author-email: jimnd55512@gmail.com
License: GPLv3
Classifier: Programming Language :: Python :: 3
Classifier: Operating System :: OS Independent
Requires-Python: >=3.8
License-File: LICENSE
Requires-Dist: prompt_toolkit>=3.0
Dynamic: author
Dynamic: author-email
Dynamic: classifier
Dynamic: home-page
Dynamic: license
Dynamic: license-file
Dynamic: requires-dist
Dynamic: requires-python
Dynamic: summary
